caterpillar/_C.pyi
caterpillar/__init__.py
caterpillar/__main__.py
caterpillar/_common.py
caterpillar/abc.py
caterpillar/byteorder.py
caterpillar/c.py
caterpillar/context.py
caterpillar/exception.py
caterpillar/options.py
caterpillar/py.py
caterpillar/py.typed
caterpillar/registry.py
caterpillar/shared.py
caterpillar/shortcuts.py
caterpillar/types.py
caterpillar/fields/__init__.py
caterpillar/fields/_base.py
caterpillar/fields/_mixin.py
caterpillar/fields/common.py
caterpillar/fields/compression.py
caterpillar/fields/conditional.py
caterpillar/fields/crypto.py
caterpillar/fields/digest.py
caterpillar/fields/hook.py
caterpillar/fields/net.py
caterpillar/fields/pointer.py
caterpillar/fields/varint.py
caterpillar/include/caterpillar/arch.h
caterpillar/include/caterpillar/atom.h
caterpillar/include/caterpillar/caterpillar.h
caterpillar/include/caterpillar/caterpillarapi.h.in
caterpillar/include/caterpillar/context.h
caterpillar/include/caterpillar/lengthinfo.h
caterpillar/include/caterpillar/macros.h
caterpillar/include/caterpillar/module.h
caterpillar/include/caterpillar/option.h
caterpillar/include/caterpillar/atoms/builtin/builtin.h
caterpillar/include/caterpillar/atoms/builtin/conditional.h
caterpillar/include/caterpillar/atoms/builtin/offset.h
caterpillar/include/caterpillar/atoms/builtin/repeated.h
caterpillar/include/caterpillar/atoms/builtin/switch.h
caterpillar/model/__init__.py
caterpillar/model/_base.py
caterpillar/model/_bitfield.py
caterpillar/model/_struct.py
caterpillar/model/_template.py
caterpillar_py-2.8.0.dist-info/METADATA
caterpillar_py-2.8.0.dist-info/WHEEL
caterpillar_py-2.8.0.dist-info/top_level.txt
caterpillar_py-2.8.0.dist-info/RECORD
