Metadata-Version: 2.4
Name: caterpillar-py
Version: 2.8.0
Summary: Library to pack and unpack structurized binary data.
Author: MatrixEditor
Maintainer: MatrixEditor
Project-URL: Homepage, https://github.com/MatrixEditor/caterpillar
Project-URL: API-Docs, https://matrixeditor.github.io/caterpillar
Classifier: Development Status :: 4 - Beta
Classifier: Intended Audience :: Developers
Classifier: Intended Audience :: Science/Research
Classifier: License :: OSI Approved :: GNU General Public License v3 (GPLv3)
Classifier: Programming Language :: Python :: 3.10
Classifier: Programming Language :: Python :: 3.11
Classifier: Programming Language :: Python :: 3.12
Classifier: Programming Language :: Python :: 3.13
Requires-Python: >=3.10
Requires-Dist: typing-extensions
Provides-Extra: lzo
Requires-Dist: lzallright; extra == "lzo"
Provides-Extra: crypt
Requires-Dist: cryptography; extra == "crypt"
Provides-Extra: all
Requires-Dist: lzallright; extra == "all"
Requires-Dist: cryptography; extra == "all"
